[
    {
        "name": "Company One",
        "address": "123 Main St, City, Country",
        "phone": "+1 (555) 123-4567",
        "website": "http://www.companyone.com",
        "image": "companyone.png",
        "membershipLevel": 1,
        "otherInfo": "Additional information about Company One."
    },
    {
        "name": "Company Two",
        "address": "456 Elm St, City, Country",
        "phone": "+1 (555) 234-5678",
        "website": "http://www.companytwo.com",
        "image": "companytwo.png",
        "membershipLevel": 2,
        "otherInfo": "Additional information about Company Two."
    },
    {
        "name": "Company Three",
        "address": "789 Oak St, City, Country",
        "phone": "+1 (555) 345-6789",
        "website": "http://www.companythree.com",
        "image": "companythree.png",
        "membershipLevel": 3,
        "otherInfo": "Additional information about Company Three."
    },
    {
        "name": "Company Four",
        "address": "101 Pine St, City, Country",
        "phone": "+1 (555) 456-7890",
        "website": "http://www.companyfour.com",
        "image": "companyfour.png",
        "membershipLevel": 1,
        "otherInfo": "Additional information about Company Four."
    },
    {
        "name": "Company Five",
        "address": "202 Maple St, City, Country",
        "phone": "+1 (555) 567-8901",
        "website": "http://www.companyfive.com",
        "image": "companyfive.png",
        "membershipLevel": 2,
        "otherInfo": "Additional information about Company Five."
    },
    {
        "name": "Company Six",
        "address": "303 Birch St, City, Country",
        "phone": "+1 (555) 678-9012",
        "website": "http://www.companysix.com",
        "image": "companysix.png",
        "membershipLevel": 3,
        "otherInfo": "Additional information about Company Six."
    },
    {
        "name": "Company Seven",
        "address": "404 Cedar St, City, Country",
        "phone": "+1 (555) 789-0123",
        "website": "http://www.companyseven.com",
        "image": "companyseven.png",
        "membershipLevel": 1,
        "otherInfo": "Additional information about Company Seven."
    }
]
